pyPuii/__init__.py
pyPuii/__main__.py
pyPuii/configs.py
pyPuii/exceptions.py
pyPuii/loader.py
pyPuii/version.py
pyPuii/_misc/__init__.py
pyPuii/_misc/_assistant.py
pyPuii/_misc/_decorators.py
pyPuii/_misc/_supporter.py
pyPuii/_misc/_wrappers.py
pyPuii/dB/__init__.py
pyPuii/dB/_core.py
pyPuii/dB/afk_db.py
pyPuii/dB/antiflood_db.py
pyPuii/dB/asst_fns.py
pyPuii/dB/asstcmd_db.py
pyPuii/dB/autoban_db.py
pyPuii/dB/blacklist_chat_db.py
pyPuii/dB/blacklist_db.py
pyPuii/dB/botchat_db.py
pyPuii/dB/broadcast_db.py
pyPuii/dB/ch_db.py
pyPuii/dB/dnd_db.py
pyPuii/dB/echo_db.py
pyPuii/dB/filestore_db.py
pyPuii/dB/filter_db.py
pyPuii/dB/forcesub_db.py
pyPuii/dB/gban_mute_db.py
pyPuii/dB/gcast_blacklist_db.py
pyPuii/dB/greetings_db.py
pyPuii/dB/logusers_db.py
pyPuii/dB/mute_db.py
pyPuii/dB/night_db.py
pyPuii/dB/notes_db.py
pyPuii/dB/nsfw_db.py
pyPuii/dB/pmpermit_db.py
pyPuii/dB/snips_db.py
pyPuii/dB/vc_sudos.py
pyPuii/dB/warn_db.py
pyPuii/functions/FastTelethon.py
pyPuii/functions/__init__.py
pyPuii/functions/admins.py
pyPuii/functions/executor.py
pyPuii/functions/gDrive.py
pyPuii/functions/google_image.py
pyPuii/functions/helper.py
pyPuii/functions/info.py
pyPuii/functions/misc.py
pyPuii/functions/tools.py
pyPuii/functions/ytdl.py
pyPuii/startup/BaseClient.py
pyPuii/startup/__init__.py
pyPuii/startup/_database.py
pyPuii/startup/_extra.py
pyPuii/startup/connections.py
pyPuii/startup/funcs.py
pyPuii/startup/loader.py
pyPuii/startup/utils.py
py_Puii-2022.6.6.dist-info/LICENSE
py_Puii-2022.6.6.dist-info/METADATA
py_Puii-2022.6.6.dist-info/WHEEL
py_Puii-2022.6.6.dist-info/top_level.txt
py_Puii-2022.6.6.dist-info/RECORD
