Metadata-Version: 2.1
Name: py-Puii
Version: 2022.6.6
Summary: A Secure and Powerful Python-Telethon Based Library For Puii Userbot.
Home-page: https://github.com/AellyXD/pyPuii
Author: AellyXD
Author-email: itsme.ananya47@gmail.com
License: GNU AFFERO GENERAL PUBLIC LICENSE (v3)
Project-URL: Bug Tracker, https://github.com/AellyXD/pyPuii/issues
Project-URL: Documentation, https://t.me/kkara9009
Project-URL: Source Code, https://github.com/AellyXD/pyPuii
Classifier: Programming Language :: Python :: 3
Classifier: Programming Language :: Python :: 3.8
Classifier: Programming Language :: Python :: 3.9
Classifier: Programming Language :: Python :: 3.10
Classifier: License :: OSI Approved :: GNU General Public License v3 (GPLv3)
Classifier: Operating System :: OS Independent
Requires-Python: >3.7, <3.11
License-File: LICENSE
Requires-Dist: redis
Requires-Dist: hiredis
Requires-Dist: python-decouple
Requires-Dist: python-dotenv
